expyre/__init__.py
expyre/__main__.py
expyre/helpers.py
expyre-0.1.4.dist-info/DESCRIPTION.rst
expyre-0.1.4.dist-info/METADATA
expyre-0.1.4.dist-info/RECORD
expyre-0.1.4.dist-info/WHEEL
expyre-0.1.4.dist-info/entry_points.txt
expyre-0.1.4.dist-info/metadata.json
expyre-0.1.4.dist-info/top_level.txt
