Metadata-Version: 2.0
Name: expyre
Version: 0.1.4
Summary: Python wrapper over `atd` to schedule deletion of files.
Home-page: https://github.com/lonetwin/expyre
Author: Steven Fernandez
Author-email: steve@lonetwin.net
License: MIT
Keywords: atd,scheduled file deletion
Platform: UNKNOWN
Classifier: Development Status :: 4 - Beta
Classifier: Intended Audience :: Developers
Classifier: Topic :: Software Development :: Libraries
Classifier: License :: OSI Approved :: MIT License
Classifier: Programming Language :: Python :: 2
Classifier: Programming Language :: Python :: 3
